Workbook
Name BAC: RawData!$A$63:$G$144
Name BAC_2020: RawData!$A$141:$G$148
Name BAC_2021: RawData!$A$126:$G$132
Name BAC_2022: RawData!$A$113:$G$124
Name BAC_2023: RawData!$A$98:$G$107
Name BAC_2024: RawData!$A$78:$G$87
Name BAC_2025: RawData!$A$63:$G$72
Name JPM: RawData!$A$2:$G$62
Name JPM_2020: RawData!#REF!
Name JPM_2021: RawData!#REF!
Name JPM_2022: RawData!$A$53:$G$62
Name JPM_2023: RawData!$A$38:$G$47
Name JPM_2024: RawData!$A$18:$G$27
Name JPM_2025: RawData!$A$2:$G$12

Sheet RawData
A1: Raw Dataset Extracted from Call Reports | I1: FFIEC Call Report Reference Guide
A2: Bank | B2: Year | C2: Schedule | D2: Line Item | E2: Code | F2: Value (000s) | G2: Source Page | I2: Category | J2: Code / Term | K2: Full Name | L2: What It Represents | M2: Why It Matters in Analysis
A3: JPM | B3: 2025 | C3: RI | D3: Net Income Attributable to Bank | E3: RIAD4340 | F3: 49644000 | G3: RI p.10 | I3: Schedule | J3: RI | K3: Report of Income | L3: Income statement section of the call report | M3: Used to compute profitability (ROA, ROE, efficiency)
A4: JPM | B4: 2025 | C4: RI | D4: Net Interest Income | E4: RIAD4074 | F4: 97846000 | G4: RI p.9 | I4: Schedule | J4: RC | K4: Balance Sheet | L4: Consolidated statement of assets & liabilities | M4: Used to compute leverage and asset composition
A5: JPM | B5: 2025 | C5: RI | D5: Total Noninterest Income | E5: RIAD4079 | F5: 66240000 | G5: RI p.10 | I5: Schedule | J5: RC-C | K5: Loans and Lease Financing Receivables | L5: Detailed breakdown of loan portfolio | M5: Used to identify total gross loans
A6: JPM | B6: 2025 | C6: RI | D6: Total Noninterest Expense | E6: RIAD4093 | F6: 86128000 | G6: RI p.10 | I6: Schedule | J6: RI-A | K6: Changes in Bank Equity Capital | L6: Reconciliation of retained earnings | M6: Used to confirm net income flows to equity
A7: JPM | B7: 2025 | C7: RI | D7: Provision for Credit Losses | E7: RIADJJ33 | F7: 13995000 | G7: RI p.9 | I7: Code | J7: RIAD4340 | K7: Net Income Attributable to Bank | L7: Final net income after all expenses and taxes | M7: Core profitability measure (numerator of ROA/ROE)
A8: JPM | B8: 2025 | C8: RC | D8: Total Assets | E8: RCFD2170 | F8: 3973004000 | G8: RC p.17 | I8: Code | J8: RIAD4074 | K8: Net Interest Income | L8: Interest income minus interest expense | M8: Core earnings from lending activities
A9: JPM | B9: 2025 | C9: RC | D9: Total Loans (Gross) | E9: RCFD2122 | F9: 1497490000 | G9: RC-C p.23 | I9: Code | J9: RIAD4079 | K9: Total Noninterest Income | L9: Fees, trading revenue, service income | M9: Diversification of revenue sources
A10: JPM | B10: 2025 | C10: RC | D10: Allowance for Credit Losses | E10: RCFD3123 | F10: 25539000 | G10: RC p.19 | I10: Code | J10: RIAD4093 | K10: Total Noninterest Expense | L10: Operating expenses (salary, admin, overhead) | M10: Used in efficiency ratio
A11: JPM | B11: 2025 | C11: RC | D11: Total Deposits | E11: RCON2200 | F11: 2440164000 | G11: RC p.18 | I11: Code | J11: RIADJJ33 | K11: Provision for Credit Losses | L11: Loan loss expense recorded in income statement | M11: Reflects credit risk conditions
A12: JPM | B12: 2025 | C12: RC | D12: Total Equity Capital | E12: RCFD3210 | F12: 344733000 | G12: RC p.20 | I12: Code | J12: RCFD2170 | K12: Total Assets | L12: Total consolidated assets | M12: Denominator of ROA and leverage ratios
A13: JPM | B13: 2024 | C13: RI | D13: Net Income Attributable to Bank | E13: RIAD4340 | F13: 52502000 | G13: RI-A p.12 | I13: Code | J13: RCFD2122 | K13: Total Loans (Gross) | L13: Total loans before deducting reserves | M13: Used in loan-to-asset and loan-to-deposit ratios
A14: JPM | B14: 2024 | C14: RI | D14: Net Interest Income | E14: RIAD4074 | F14: 94192000 | G14: RI p.9 | I14: Code | J14: RCFD3123 | K14: Allowance for Credit Losses | L14: Reserve for expected loan losses | M14: Credit risk cushion
... A16: JPM | B16: 2024 | C16: RI | D16: Total Noninterest Expense | E16: RIAD4093 | F16: 82964000 | G16: RI p.10 | I16: Code | J16: RCFD3210 | K16: Total Equity Capital | L16: Total shareholder equity | M16: Used in ROE and equity multiplier
A17: JPM | B17: 2024 | C17: RI | D17: Provision for Credit Losses | E17: RIADJJ33 | F17: 13439000 | G17: RI p.9
A18: JPM | B18: 2024 | C18: RC | D18: Total Assets | E18: RCFD2170 | F18: 3875396000 | G18: RC p.17
A19: JPM | B19: 2024 | C19: RC | D19: Total Loans (Gross) | E19: RCFD2122 | F19: 1410623000 | G19: RC-C p.23
A20: JPM | B20: 2024 | C20: RC | D20: Allowance for Credit Losses | E20: RCFD3123 | F20: 23782000 | G20: RC p.19
A21: JPM | B21: 2024 | C21: RC | D21: Total Deposits | E21: RCON2200 | F21: 2379642000 | G21: RC p.18
A22: JPM | B22: 2024 | C22: RC | D22: Total Equity Capital | E22: RCFD3210 | F22: 328451000 | G22: RC p.20
A23: JPM | B23: 2023 | C23: RI | D23: Net Income Attributable to Bank | E23: RIAD4340 | F23: 49552000 | G23: RI-A p.12
A24: JPM | B24: 2023 | C24: RI | D24: Net Interest Income | E24: RIAD4074 | F24: 89283000 | G24: RI p.9
A25: JPM | B25: 2023 | C25: RI | D25: Total Noninterest Income | E25: RIAD4079 | F25: 60724000 | G25: RI p.10
A26: JPM | B26: 2023 | C26: RI | D26: Total Noninterest Expense | E26: RIAD4093 | F26: 80173000 | G26: RI p.10
A27: JPM | B27: 2023 | C27: RI | D27: Provision for Credit Losses | E27: RIADJJ33 | F27: 8150000 | G27: RI p.9
A28: JPM | B28: 2023 | C28: RC | D28: Total Assets | E28: RCFD2170 | F28: 3736765000 | G28: RC p.17
... A362: Rockland Trust | B362: 2020 | C362: RC | D362: Total Equity Capital | E362: RCON3210 | F362: 2470655 | G362: RI-A p.12

Sheet Calculated Ratio
A1: Bank | B1: Year | C1: Net Income | D1: Total Assets | E1: Equity | F1: Loans | G1: Deposits | H1: NII | I1: Noninterest Income | J1: Noninterest Expense | K1: ROA | L1: ROE | M1: Equity Multiplier | N1: Loan/Asset | O1: Loan/Deposit | P1: Efficiency Ratio
A2: JPM | B2: 2025 | C2: =SUMIFS(RawData!F:F, RawData!A:A,A2, RawData!B:B,B2, RawData!E:E,"RIAD4340") -> 49644000 | D2: {=_xlfn.XLOOKUP(1,(RawData!$A:$A=A2)*(RawData!$B:$B=B2)*(RawData!$D:$D="Total Assets"),RawData!$F:$F)} -> 3973004000 | E2: {=_xlfn.XLOOKUP(1,(RawData!$A:$A=A2)*(RawData!$B:$B=B2)*(RawData!$D:$D="Total Equity Capital"),RawData!$F:$F)} -> 344733000 | F2: {=_xlfn.XLOOKUP(1,(RawData!$A:$A=A2)*(RawData!$B:$B=B2)*(RawData!$D:$D="Total Loans (Gross)"),RawData!$F:$F)} -> 1497490000 | G2: =SUMIFS(RawData!F:F, RawData!A:A,A2, RawData!B:B,B2, RawData!E:E,"RCON2200") -> 2440164000 | H2: =SUMIFS(RawData!F:F, RawData!A:A,A2, RawData!B:B,B2, RawData!E:E,"RIAD4074") -> 97846000 | I2: =SUMIFS(RawData!F:F, RawData!A:A,A2, RawData!B:B,B2, RawData!E:E,"RIAD4079") -> 66240000 | J2: =SUMIFS(RawData!F:F, RawData!A:A,A2, RawData!B:B,B2, RawData!E:E,"RIAD4093") -> 86128000 | K2: =C2/D2 -> 0.012495331 | L2: =C2/E2 -> 0.1440071 | M2: =D2/E2 -> 11.524873 | N2: =F2/D2 -> 0.37691631 | O2: =F2/G2 -> 0.61368416 | P2: =J2/(H2+I2) -> 0.52489548
A3: JPM | B3: 2024 | C3: =SUMIFS(RawData!F:F, RawData!A:A,A3, RawData!B:B,B3, RawData!E:E,"RIAD4340") -> 52502000 | D3: {=_xlfn.XLOOKUP(1,(RawData!$A:$A=A3)*(RawData!$B:$B=B3)*(RawData!$D:$D="Total Assets"),RawData!$F:$F)} -> 3875396000 | E3: {=_xlfn.XLOOKUP(1,(RawData!$A:$A=A3)*(RawData!$B:$B=B3)*(RawData!$D:$D="Total Equity Capital"),RawData!$F:$F)} -> 328451000 | F3: {=_xlfn.XLOOKUP(1,(RawData!$A:$A=A3)*(RawData!$B:$B=B3)*(RawData!$D:$D="Total Loans (Gross)"),RawData!$F:$F)} -> 1410623000 | G3: =SUMIFS(RawData!F:F, RawData!A:A,A3, RawData!B:B,B3, RawData!E:E,"RCON2200") -> 2379642000 | H3: =SUMIFS(RawData!F:F, RawData!A:A,A3, RawData!B:B,B3, RawData!E:E,"RIAD4074") -> 94192000 | I3: =SUMIFS(RawData!F:F, RawData!A:A,A3, RawData!B:B,B3, RawData!E:E,"RIAD4079") -> 63459000 | J3: =SUMIFS(RawData!F:F, RawData!A:A,A3, RawData!B:B,B3, RawData!E:E,"RIAD4093") -> 82964000 | K3: =C3/D3 -> 0.013547519 | L3: =C3/E3 -> 0.15984728 | M3: =D3/E3 -> 11.799008 | N3: =F3/D3 -> 0.36399454 | O3: =F3/G3 -> 0.59278791 | P3: =J3/(H3+I3) -> 0.52625102
A4: JPM | B4: 2023 | C4: =SUMIFS(RawData!F:F, RawData!A:A,A4, RawData!B:B,B4, RawData!E:E,"RIAD4340") -> 49552000 | D4: {=_xlfn.XLOOKUP(1,(RawData!$A:$A=A4)*(RawData!$B:$B=B4)*(RawData!$D:$D="Total Assets"),RawData!$F:$F)} -> 3736765000 | E4: {=_xlfn.XLOOKUP(1,(RawData!$A:$A=A4)*(RawData!$B:$B=B4)*(RawData!$D:$D="Total Equity Capital"),RawData!$F:$F)} -> 299218000 | F4: {=_xlfn.XLOOKUP(1,(RawData!$A:$A=A4)*(RawData!$B:$B=B4)*(RawData!$D:$D="Total Loans (Gross)"),RawData!$F:$F)} -> 1341628000 | G4: =SUMIFS(RawData!F:F, RawData!A:A,A4, RawData!B:B,B4, RawData!E:E,"RCON2200") -> 2308845000 | H4: =SUMIFS(RawData!F:F, RawData!A:A,A4, RawData!B:B,B4, RawData!E:E,"RIAD4074") -> 89283000 | I4: =SUMIFS(RawData!F:F, RawData!A:A,A4, RawData!B:B,B4, RawData!E:E,"RIAD4079") -> 60724000 | J4: =SUMIFS(RawData!F:F, RawData!A:A,A4, RawData!B:B,B4, RawData!E:E,"RIAD4093") -> 80173000 | K4: =C4/D4 -> 0.013260668 | L4: =C4/E4 -> 0.16560501 | M4: =D4/E4 -> 12.488437 | N4: =F4/D4 -> 0.35903462 | O4: =F4/G4 -> 0.58108188 | P4: =J4/(H4+I4) -> 0.53446173
A5: JPM | B5: 2022 | C5: =SUMIFS(RawData!F:F, RawData!A:A,A5, RawData!B:B,B5, RawData!E:E,"RIAD4340") -> 37676000 | D5: {=_xlfn.XLOOKUP(1,(RawData!$A:$A=A5)*(RawData!$B:$B=B5)*(RawData!$D:$D="Total Assets"),RawData!$F:$F)} -> 3665743000 | E5: {=_xlfn.XLOOKUP(1,(RawData!$A:$A=A5)*(RawData!$B:$B=B5)*(RawData!$D:$D="Total Equity Capital"),RawData!$F:$F)} -> 297936000 | F5: {=_xlfn.XLOOKUP(1,(RawData!$A:$A=A5)*(RawData!$B:$B=B5)*(RawData!$D:$D="Total Loans (Gross)"),RawData!$F:$F)} -> 1210388000 | G5: =SUMIFS(RawData!F:F, RawData!A:A,A5, RawData!B:B,B5, RawData!E:E,"RCON2200") -> 2334905000 | H5: =SUMIFS(RawData!F:F, RawData!A:A,A5, RawData!B:B,B5, RawData!E:E,"RIAD4074") -> 67154000 | I5: =SUMIFS(RawData!F:F, RawData!A:A,A5, RawData!B:B,B5, RawData!E:E,"RIAD4079") -> 58832000 | J5: =SUMIFS(RawData!F:F, RawData!A:A,A5, RawData!B:B,B5, RawData!E:E,"RIAD4093") -> 77189000 | K5: =C5/D5 -> 0.010277862 | L5: =C5/E5 -> 0.12645669 | M5: =D5/E5 -> 12.303793 | N5: =F5/D5 -> 0.330189 | O5: =F5/G5 -> 0.51838854 | P5: =J5/(H5+I5) -> 0.61267919
A6: JPM | B6: 2021 | C6: =SUMIFS(RawData!F:F, RawData!A:A,A6, RawData!B:B,B6, RawData!E:E,"RIAD4340") -> 48334000 | D6: {=_xlfn.XLOOKUP(1,(RawData!$A:$A=A6)*(RawData!$B:$B=B6)*(RawData!$D:$D="Total Assets"),RawData!$F:$F)} -> 3167893000 | E6: {=_xlfn.XLOOKUP(1,(RawData!$A:$A=A6)*(RawData!$B:$B=B6)*(RawData!$D:$D="Total Equity Capital"),RawData!$F:$F)} -> 280360000 | F6: {=_xlfn.XLOOKUP(1,(RawData!$A:$A=A6)*(RawData!$B:$B=B6)*(RawData!$D:$D="Total Loans (Gross)"),RawData!$F:$F)} -> 1065070000 | G6: =SUMIFS(RawData!F:F, RawData!A:A,A6, RawData!B:B,B6, RawData!E:E,"RCON2200") -> 2373667000 | H6: =SUMIFS(RawData!F:F, RawData!A:A,A6, RawData!B:B,B6, RawData!E:E,"RIAD4074") -> 52966000 | I6: =SUMIFS(RawData!F:F, RawData!A:A,A6, RawData!B:B,B6, RawData!E:E,"RIAD4079") -> 59682000 | J6: =SUMIFS(RawData!F:F, RawData!A:A,A6, RawData!B:B,B6, RawData!E:E,"RIAD4093") -> 71802000 | K6: =C6/D6 -> 0.01525746 | L6: =C6/E6 -> 0.17239977 | M6: =D6/E6 -> 11.299376 | N6: =F6/D6 -> 0.33620769 | O6: =F6/G6 -> 0.44870237 | P6: =J6/(H6+I6) -> 0.63740146
A7: JPM | B7: 2020 | C7: =SUMIFS(RawData!F:F, RawData!A:A,A7, RawData!B:B,B7, RawData!E:E,"RIAD4340") -> 21032000 | D7: {=_xlfn.XLOOKUP(1,(RawData!$A:$A=A7)*(RawData!$B:$B=B7)*(RawData!$D:$D="Total Assets"),RawData!$F:$F)} -> 3386071000 | E7: {=_xlfn.XLOOKUP(1,(RawData!$A:$A=A7)*(RawData!$B:$B=B7)*(RawData!$D:$D="Total Equity Capital"),RawData!$F:$F)} -> 270060000 | F7: {=_xlfn.XLOOKUP(1,(RawData!$A:$A=A7)*(RawData!$B:$B=B7)*(RawData!$D:$D="Total Loans (Gross)"),RawData!$F:$F)} -> 1037654000 | G7: =SUMIFS(RawData!F:F, RawData!A:A,A7, RawData!B:B,B7, RawData!E:E,"RCON2200") -> 2312125000 | H7: =SUMIFS(RawData!F:F, RawData!A:A,A7, RawData!B:B,B7, RawData!E:E,"RIAD4074") -> 55294000 | I7: =SUMIFS(RawData!F:F, RawData!A:A,A7, RawData!B:B,B7, RawData!E:E,"RIAD4079") -> 61104000 | J7: =SUMIFS(RawData!F:F, RawData!A:A,A7, RawData!B:B,B7, RawData!E:E,"RIAD4093") -> 69354000 | K7: =C7/D7 -> 0.0062113287 | L7: =C7/E7 -> 0.07787899 | M7: =D7/E7 -> 12.538217 | N7: =F7/D7 -> 0.3064478 | O7: =F7/G7 -> 0.44878802 | P7: =J7/(H7+I7) -> 0.59583498
A8: BAC | B8: 2025 | C8: =SUMIFS(RawData!F:F, RawData!A:A,A8, RawData!B:B,B8, RawData!E:E,"RIAD4340") -> 84000 | D8: {=_xlfn.XLOOKUP(1,(RawData!$A:$A=A8)*(RawData!$B:$B=B8)*(RawData!$D:$D="Total Assets"),RawData!$F:$F)} -> 1177000 | E8: {=_xlfn.XLOOKUP(1,(RawData!$A:$A=A8)*(RawData!$B:$B=B8)*(RawData!$D:$D="Total Equity Capital"),RawData!$F:$F)} -> 101000 | F8: {=_xlfn.XLOOKUP(1,(RawData!$A:$A=A8)*(RawData!$B:$B=B8)*(RawData!$D:$D="Total Loans (Gross)"),RawData!$F:$F)} -> 733000 | G8: =SUMIFS(RawData!F:F, RawData!A:A,A8, RawData!B:B,B8, RawData!E:E,"RCON2200") -> 1060000 | H8: =SUMIFS(RawData!F:F, RawData!A:A,A8, RawData!B:B,B8, RawData!E:E,"RIAD4074") -> 238000 | I8: =SUMIFS(RawData!F:F, RawData!A:A,A8, RawData!B:B,B8, RawData!E:E,"RIAD4079") -> 1000 | J8: =SUMIFS(RawData!F:F, RawData!A:A,A8, RawData!B:B,B8, RawData!E:E,"RIAD4093") -> 125000 | K8: =C8/D8 -> 0.071367884 | L8: =C8/E8 -> 0.83168317 | M8: =D8/E8 -> 11.653465 | N8: =F8/D8 -> 0.62276975 | O8: =F8/G8 -> 0.69150943 | P8: =J8/(H8+I8) -> 0.52301255
A9: BAC | B9: 2024 | C9: =SUMIFS(RawData!F:F, RawData!A:A,A9, RawData!B:B,B9, RawData!E:E,"RIAD4340") -> 69000 | D9: {=_xlfn.XLOOKUP(1,(RawData!$A:$A=A9)*(RawData!$B:$B=B9)*(RawData!$D:$D="Total Assets"),RawData!$F:$F)} -> 1104000 | E9: {=_xlfn.XLOOKUP(1,(RawData!$A:$A=A9)*(RawData!$B:$B=B9)*(RawData!$D:$D="Total Equity Capital"),RawData!$F:$F)} -> 92000 | F9: {=_xlfn.XLOOKUP(1,(RawData!$A:$A=A9)*(RawData!$B:$B=B9)*(RawData!$D:$D="Total Loans (Gross)"),RawData!$F:$F)} -> 682000 | G9: =SUMIFS(RawData!F:F, RawData!A:A,A9, RawData!B:B,B9, RawData!E:E,"RCON2200") -> 1002000 | H9: =SUMIFS(RawData!F:F, RawData!A:A,A9, RawData!B:B,B9, RawData!E:E,"RIAD4074") -> 169000 | I9: =SUMIFS(RawData!F:F, RawData!A:A,A9, RawData!B:B,B9, RawData!E:E,"RIAD4079") -> -2000 | J9: =SUMIFS(RawData!F:F, RawData!A:A,A9, RawData!B:B,B9, RawData!E:E,"RIAD4093") -> 75000 | K9: =C9/D9 -> 0.0625 | L9: =C9/E9 -> 0.75 | M9: =D9/E9 -> 12 | N9: =F9/D9 -> 0.61775362 | O9: =F9/G9 -> 0.68063872 | P9: =J9/(H9+I9) -> 0.4491018
A10: BAC | B10: 2023 | C10: =SUMIFS(RawData!F:F, RawData!A:A,A10, RawData!B:B,B10, RawData!E:E,"RIAD4340") -> 63000 | D10: {=_xlfn.XLOOKUP(1,(RawData!$A:$A=A10)*(RawData!$B:$B=B10)*(RawData!$D:$D="Total Assets"),RawData!$F:$F)} -> 1046000 | E10: {=_xlfn.XLOOKUP(1,(RawData!$A:$A=A10)*(RawData!$B:$B=B10)*(RawData!$D:$D="Total Equity Capital"),RawData!$F:$F)} -> 87000 | F10: {=_xlfn.XLOOKUP(1,(RawData!$A:$A=A10)*(RawData!$B:$B=B10)*(RawData!$D:$D="Total Loans (Gross)"),RawData!$F:$F)} -> 631000 | G10: =SUMIFS(RawData!F:F, RawData!A:A,A10, RawData!B:B,B10, RawData!E:E,"RCON2200") -> 946000 | H10: =SUMIFS(RawData!F:F, RawData!A:A,A10, RawData!B:B,B10, RawData!E:E,"RIAD4074") -> 154000 | I10: =SUMIFS(RawData!F:F, RawData!A:A,A10, RawData!B:B,B10, RawData!E:E,"RIAD4079") -> -1000 | J10: =SUMIFS(RawData!F:F, RawData!A:A,A10, RawData!B:B,B10, RawData!E:E,"RIAD4093") -> 71000 | K10: =C10/D10 -> 0.060229446 | L10: =C10/E10 -> 0.72413793 | M10: =D10/E10 -> 12.022989 | N10: =F10/D10 -> 0.60325048 | O10: =F10/G10 -> 0.66701903 | P10: =J10/(H10+I10) -> 0.46405229
A11: BAC | B11: 2022 | C11: =SUMIFS(RawData!F:F, RawData!A:A,A11, RawData!B:B,B11, RawData!E:E,"RIAD4340") -> 55000 | D11: {=_xlfn.XLOOKUP(1,(RawData!$A:$A=A11)*(RawData!$B:$B=B11)*(RawData!$D:$D="Total Assets"),RawData!$F:$F)} -> 1012000 | E11: {=_xlfn.XLOOKUP(1,(RawData!$A:$A=A11)*(RawData!$B:$B=B11)*(RawData!$D:$D="Total Equity Capital"),RawData!$F:$F)} -> 84000 | F11: {=_xlfn.XLOOKUP(1,(RawData!$A:$A=A11)*(RawData!$B:$B=B11)*(RawData!$D:$D="Total Loans (Gross)"),RawData!$F:$F)} -> 604000 | G11: =SUMIFS(RawData!F:F, RawData!A:A,A11, RawData!B:B,B11, RawData!E:E,"RCON2200") -> 923000 | H11: =SUMIFS(RawData!F:F, RawData!A:A,A11, RawData!B:B,B11, RawData!E:E,"RIAD4074") -> 140000 | I11: =SUMIFS(RawData!F:F, RawData!A:A,A11, RawData!B:B,B11, RawData!E:E,"RIAD4079") -> -3000 | J11: =SUMIFS(RawData!F:F, RawData!A:A,A11, RawData!B:B,B11, RawData!E:E,"RIAD4093") -> 68000 | K11: =C11/D11 -> 0.054347826 | L11: =C11/E11 -> 0.6547619 | M11: =D11/E11 -> 12.047619 | N11: =F11/D11 -> 0.59683794 | O11: =F11/G11 -> 0.65438787 | P11: =J11/(H11+I11) -> 0.49635036
A12: BAC | B12: 2021 | C12: =SUMIFS(RawData!F:F, RawData!A:A,A12, RawData!B:B,B12, RawData!E:E,"RIAD4340") -> 47000 | D12: {=_xlfn.XLOOKUP(1,(RawData!$A:$A=A12)*(RawData!$B:$B=B12)*(RawData!$D:$D="Total Assets"),RawData!$F:$F)} -> 978000 | E12: {=_xlfn.XLOOKUP(1,(RawData!$A:$A=A12)*(RawData!$B:$B=B12)*(RawData!$D:$D="Total Equity Capital"),RawData!$F:$F)} -> 81000 | F12: {=_xlfn.XLOOKUP(1,(RawData!$A:$A=A12)*(RawData!$B:$B=B12)*(RawData!$D:$D="Total Loans (Gross)"),RawData!$F:$F)} -> 589000 | G12: =SUMIFS(RawData!F:F, RawData!A:A,A12, RawData!B:B,B12, RawData!E:E,"RCON2200") -> 905000 | H12: =SUMIFS(RawData!F:F, RawData!A:A,A12, RawData!B:B,B12, RawData!E:E,"RIAD4074") -> 130000 | I12: =SUMIFS(RawData!F:F, RawData!A:A,A12, RawData!B:B,B12, RawData!E:E,"RIAD4079") -> -4000 | J12: =SUMIFS(RawData!F:F, RawData!A:A,A12, RawData!B:B,B12, RawData!E:E,"RIAD4093") -> 65000 | K12: =C12/D12 -> 0.04805726 | L12: =C12/E12 -> 0.58024691 | M12: =D12/E12 -> 12.074074 | N12: =F12/D12 -> 0.60224949 | O12: =F12/G12 -> 0.65082873 | P12: =J12/(H12+I12) -> 0.51587302
A13: BAC | B13: 2020 | C13: =SUMIFS(RawData!F:F, RawData!A:A,A13, RawData!B:B,B13, RawData!E:E,"RIAD4340") -> 39000 | D13: {=_xlfn.XLOOKUP(1,(RawData!$A:$A=A13)*(RawData!$B:$B=B13)*(RawData!$D:$D="Total Assets"),RawData!$F:$F)} -> 954000 | E13: {=_xlfn.XLOOKUP(1,(RawData!$A:$A=A13)*(RawData!$B:$B=B13)*(RawData!$D:$D="Total Equity Capital"),RawData!$F:$F)} -> 78000 | F13: {=_xlfn.XLOOKUP(1,(RawData!$A:$A=A13)*(RawData!$B:$B=B13)*(RawData!$D:$D="Total Loans (Gross)"),RawData!$F:$F)} -> 575000 | G13: =SUMIFS(RawData!F:F, RawData!A:A,A13, RawData!B:B,B13, RawData!E:E,"RCON2200") -> 889000 | H13: =SUMIFS(RawData!F:F, RawData!A:A,A13, RawData!B:B,B13, RawData!E:E,"RIAD4074") -> 122000 | I13: =SUMIFS(RawData!F:F, RawData!A:A,A13, RawData!B:B,B13, RawData!E:E,"RIAD4079") -> -6000 | J13: =SUMIFS(RawData!F:F, RawData!A:A,A13, RawData!B:B,B13, RawData!E:E,"RIAD4093") -> 63000 | K13: =C13/D13 -> 0.040880503 | L13: =C13/E13 -> 0.5 | M13: =D13/E13 -> 12.230769 | N13: =F13/D13 -> 0.60272537 | O13: =F13/G13 -> 0.64679415 | P13: =J13/(H13+I13) -> 0.54310345
... A23: TRUIST | B23: 2022 | C23: =SUMIFS(RawData!F:F, RawData!A:A,A23, RawData!B:B,B23, RawData!E:E,"RIAD4340") -> 5970000 | D23: {=_xlfn.XLOOKUP(1,(RawData!$A:$A=A23)*(RawData!$B:$B=B23)*(RawData!$D:$D="Total Assets"),RawData!$F:$F)} -> 563900000 | E23: {=_xlfn.XLOOKUP(1,(RawData!$A:$A=A23)*(RawData!$B:$B=B23)*(RawData!$D:$D="Total Equity Capital"),RawData!$F:$F)} -> 53700000 | F23: {=_xlfn.XLOOKUP(1,(RawData!$A:$A=A23)*(RawData!$B:$B=B23)*(RawData!$D:$D="Total Loans (Gross)"),RawData!$F:$F)} -> 338100000 | G23: =SUMIFS(RawData!F:F, RawData!A:A,A23, RawData!B:B,B23, RawData!E:E,"RCON2200") -> 435800000 | H23: =SUMIFS(RawData!F:F, RawData!A:A,A23, RawData!B:B,B23, RawData!E:E,"RIAD4074") -> 16430000 | I23: =SUMIFS(RawData!F:F, RawData!A:A,A23, RawData!B:B,B23, RawData!E:E,"RIAD4079") -> 5980000 | J23: =SUMIFS(RawData!F:F, RawData!A:A,A23, RawData!B:B,B23, RawData!E:E,"RIAD4093") -> 12940000 | K23: =C23/D23 -> 0.010586984 | L23: =C23/E23 -> 0.11117318 | M23: =D23/E23 -> 10.500931 | N23: =F23/D23 -> 0.59957439 | O23: =F23/G23 -> 0.77581459 | P23: =J23/(H23+I23) -> 0.57742079
A24: TRUIST | B24: 2021 | C24: =SUMIFS(RawData!F:F, RawData!A:A,A24, RawData!B:B,B24, RawData!E:E,"RIAD4340") -> 5569000 | D24: {=_xlfn.XLOOKUP(1,(RawData!$A:$A=A24)*(RawData!$B:$B=B24)*(RawData!$D:$D="Total Assets"),RawData!$F:$F)} -> 541200000 | E24: {=_xlfn.XLOOKUP(1,(RawData!$A:$A=A24)*(RawData!$B:$B=B24)*(RawData!$D:$D="Total Equity Capital"),RawData!$F:$F)} -> 52100000 | F24: {=_xlfn.XLOOKUP(1,(RawData!$A:$A=A24)*(RawData!$B:$B=B24)*(RawData!$D:$D="Total Loans (Gross)"),RawData!$F:$F)} -> 309400000 | G24: =SUMIFS(RawData!F:F, RawData!A:A,A24, RawData!B:B,B24, RawData!E:E,"RCON2200") -> 428200000 | H24: =SUMIFS(RawData!F:F, RawData!A:A,A24, RawData!B:B,B24, RawData!E:E,"RIAD4074") -> 12371000 | I24: =SUMIFS(RawData!F:F, RawData!A:A,A24, RawData!B:B,B24, RawData!E:E,"RIAD4079") -> 7310000 | J24: =SUMIFS(RawData!F:F, RawData!A:A,A24, RawData!B:B,B24, RawData!E:E,"RIAD4093") -> 13790000 | K24: =C24/D24 -> 0.010290096 | L24: =C24/E24 -> 0.1068906 | M24: =D24/E24 -> 10.387716 | N24: =F24/D24 -> 0.57169254 | O24: =F24/G24 -> 0.72255955 | P24: =J24/(H24+I24) -> 0.70067578 | R24: Formulas
A25: TRUIST | B25: 2020 | C25: =SUMIFS(RawData!F:F, RawData!A:A,A25, RawData!B:B,B25, RawData!E:E,"RIAD4340") -> 1370000 | D25: {=_xlfn.XLOOKUP(1,(RawData!$A:$A=A25)*(RawData!$B:$B=B25)*(RawData!$D:$D="Total Assets"),RawData!$F:$F)} -> 509300000 | E25: {=_xlfn.XLOOKUP(1,(RawData!$A:$A=A25)*(RawData!$B:$B=B25)*(RawData!$D:$D="Total Equity Capital"),RawData!$F:$F)} -> 51300000 | F25: {=_xlfn.XLOOKUP(1,(RawData!$A:$A=A25)*(RawData!$B:$B=B25)*(RawData!$D:$D="Total Loans (Gross)"),RawData!$F:$F)} -> 296800000 | G25: =SUMIFS(RawData!F:F, RawData!A:A,A25, RawData!B:B,B25, RawData!E:E,"RCON2200") -> 392600000 | H25: =SUMIFS(RawData!F:F, RawData!A:A,A25, RawData!B:B,B25, RawData!E:E,"RIAD4074") -> 12640000 | I25: =SUMIFS(RawData!F:F, RawData!A:A,A25, RawData!B:B,B25, RawData!E:E,"RIAD4079") -> 6320000 | J25: =SUMIFS(RawData!F:F, RawData!A:A,A25, RawData!B:B,B25, RawData!E:E,"RIAD4093") -> 14210000 | K25: =C25/D25 -> 0.0026899666 | L25: =C25/E25 -> 0.026705653 | M25: =D25/E25 -> 9.9278752 | N25: =F25/D25 -> 0.58276065 | O25: =F25/G25 -> 0.75598574 | P25: =J25/(H25+I25) -> 0.74947257 | R25: =C1 -> Net Income | S25: =_xlfn.FORMULATEXT(C2) -> =SUMIFS(RawData!F:F, RawData!A:A,A2, RawData!B:B,B2, RawData!E:E,"RIAD4340")
A26: Community Trust KY | B26: 2025 | C26: =SUMIFS(RawData!F:F, RawData!A:A,A26, RawData!B:B,B26, RawData!E:E,"RIAD4340") -> 96231 | D26: {=_xlfn.XLOOKUP(1,(RawData!$A:$A=A26)*(RawData!$B:$B=B26)*(RawData!$D:$D="Total Assets"),RawData!$F:$F)} -> 6084536 | E26: {=_xlfn.XLOOKUP(1,(RawData!$A:$A=A26)*(RawData!$B:$B=B26)*(RawData!$D:$D="Total Equity Capital"),RawData!$F:$F)} -> 624611 | F26: {=_xlfn.XLOOKUP(1,(RawData!$A:$A=A26)*(RawData!$B:$B=B26)*(RawData!$D:$D="Total Loans (Gross)"),RawData!$F:$F)} -> 4221845 | G26: =SUMIFS(RawData!F:F, RawData!A:A,A26, RawData!B:B,B26, RawData!E:E,"RCON2200") -> 5324770 | H26: =SUMIFS(RawData!F:F, RawData!A:A,A26, RawData!B:B,B26, RawData!E:E,"RIAD4074") -> 221396 | I26: =SUMIFS(RawData!F:F, RawData!A:A,A26, RawData!B:B,B26, RawData!E:E,"RIAD4079") -> 44791 | J26: =SUMIFS(RawData!F:F, RawData!A:A,A26, RawData!B:B,B26, RawData!E:E,"RIAD4093") -> 128957 | K26: =C26/D26 -> 0.015815668 | L26: =C26/E26 -> 0.15406549 | M26: =D26/E26 -> 9.7413206 | N26: =F26/D26 -> 0.69386474 | O26: =F26/G26 -> 0.79286899 | P26: =J26/(H26+I26) -> 0.48446017 | R26: =D1 -> Total Assets | S26: =_xlfn.FORMULATEXT(D2) -> =XLOOKUP(1,(RawData!$A:$A=A2)*(RawData!$B:$B=B2)*(RawData!$D:$D="Total Assets"),RawData!$F:$F)
A27: Community Trust KY | B27: 2024 | C27: =SUMIFS(RawData!F:F, RawData!A:A,A27, RawData!B:B,B27, RawData!E:E,"RIAD4340") -> 91884 | D27: {=_xlfn.XLOOKUP(1,(RawData!$A:$A=A27)*(RawData!$B:$B=B27)*(RawData!$D:$D="Total Assets"),RawData!$F:$F)} -> 5987219 | E27: {=_xlfn.XLOOKUP(1,(RawData!$A:$A=A27)*(RawData!$B:$B=B27)*(RawData!$D:$D="Total Equity Capital"),RawData!$F:$F)} -> 596802 | F27: {=_xlfn.XLOOKUP(1,(RawData!$A:$A=A27)*(RawData!$B:$B=B27)*(RawData!$D:$D="Total Loans (Gross)"),RawData!$F:$F)} -> 4082456 | G27: =SUMIFS(RawData!F:F, RawData!A:A,A27, RawData!B:B,B27, RawData!E:E,"RCON2200") -> 5216093 | H27: =SUMIFS(RawData!F:F, RawData!A:A,A27, RawData!B:B,B27, RawData!E:E,"RIAD4074") -> 214772 | I27: =SUMIFS(RawData!F:F, RawData!A:A,A27, RawData!B:B,B27, RawData!E:E,"RIAD4079") -> 43266 | J27: =SUMIFS(RawData!F:F, RawData!A:A,A27, RawData!B:B,B27, RawData!E:E,"RIAD4093") -> 124508 | K27: =C27/D27 -> 0.015346691 | L27: =C27/E27 -> 0.15396061 | M27: =D27/E27 -> 10.03217 | N27: =F27/D27 -> 0.68186181 | O27: =F27/G27 -> 0.78266549 | P27: =J27/(H27+I27) -> 0.48251808 | R27: =E1 -> Equity | S27: =_xlfn.FORMULATEXT(E2) -> =XLOOKUP(1,(RawData!$A:$A=A2)*(RawData!$B:$B=B2)*(RawData!$D:$D="Total Equity Capital"),RawData!$F:$F)
A28: Community Trust KY | B28: 2023 | C28: =SUMIFS(RawData!F:F, RawData!A:A,A28, RawData!B:B,B28, RawData!E:E,"RIAD4340") -> 88021 | D28: {=_xlfn.XLOOKUP(1,(RawData!$A:$A=A28)*(RawData!$B:$B=B28)*(RawData!$D:$D="Total Assets"),RawData!$F:$F)} -> 5742390 | E28: {=_xlfn.XLOOKUP(1,(RawData!$A:$A=A28)*(RawData!$B:$B=B28)*(RawData!$D:$D="Total Equity Capital"),RawData!$F:$F)} -> 570384 | F28: {=_xlfn.XLOOKUP(1,(RawData!$A:$A=A28)*(RawData!$B:$B=B28)*(RawData!$D:$D="Total Loans (Gross)"),RawData!$F:$F)} -> 3884772 | G28: =SUMIFS(RawData!F:F, RawData!A:A,A28, RawData!B:B,B28, RawData!E:E,"RCON2200") -> 4989551 | H28: =SUMIFS(RawData!F:F, RawData!A:A,A28, RawData!B:B,B28, RawData!E:E,"RIAD4074") -> 198654 | I28: =SUMIFS(RawData!F:F, RawData!A:A,A28, RawData!B:B,B28, RawData!E:E,"RIAD4079") -> 42118 | J28: =SUMIFS(RawData!F:F, RawData!A:A,A28, RawData!B:B,B28, RawData!E:E,"RIAD4093") -> 120442 | K28: =C28/D28 -> 0.015328287 | L28: =C28/E28 -> 0.15431884 | M28: =D28/E28 -> 10.067586 | N28: =F28/D28 -> 0.67650787 | O28: =F28/G28 -> 0.77858148 | P28: =J28/(H28+I28) -> 0.50023259 | R28: =F1 -> Loans | S28: =_xlfn.FORMULATEXT(F2) -> =XLOOKUP(1,(RawData!$A:$A=A2)*(RawData!$B:$B=B2)*(RawData!$D:$D="Total Loans (Gross)"),RawData!$F:$F)
A29: Community Trust KY | B29: 2022 | C29: =SUMIFS(RawData!F:F, RawData!A:A,A29, RawData!B:B,B29, RawData!E:E,"RIAD4340") -> 84215 | D29: {=_xlfn.XLOOKUP(1,(RawData!$A:$A=A29)*(RawData!$B:$B=B29)*(RawData!$D:$D="Total Assets"),RawData!$F:$F)} -> 5431278 | E29: {=_xlfn.XLOOKUP(1,(RawData!$A:$A=A29)*(RawData!$B:$B=B29)*(RawData!$D:$D="Total Equity Capital"),RawData!$F:$F)} -> 541603 | F29: {=_xlfn.XLOOKUP(1,(RawData!$A:$A=A29)*(RawData!$B:$B=B29)*(RawData!$D:$D="Total Loans (Gross)"),RawData!$F:$F)} -> 3650842 | G29: =SUMIFS(RawData!F:F, RawData!A:A,A29, RawData!B:B,B29, RawData!E:E,"RCON2200") -> 4723615 | H29: =SUMIFS(RawData!F:F, RawData!A:A,A29, RawData!B:B,B29, RawData!E:E,"RIAD4074") -> 182307 | I29: =SUMIFS(RawData!F:F, RawData!A:A,A29, RawData!B:B,B29, RawData!E:E,"RIAD4079") -> 40985 | J29: =SUMIFS(RawData!F:F, RawData!A:A,A29, RawData!B:B,B29, RawData!E:E,"RIAD4093") -> 116770 | K29: =C29/D29 -> 0.015505559 | L29: =C29/E29 -> 0.15549212 | M29: =D29/E29 -> 10.028153 | N29: =F29/D29 -> 0.67218839 | O29: =F29/G29 -> 0.77289152 | P29: =J29/(H29+I29) -> 0.52294753 | R29: =G1 -> Deposits | S29: =_xlfn.FORMULATEXT(G2) -> =SUMIFS(RawData!F:F, RawData!A:A,A2, RawData!B:B,B2, RawData!E:E,"RCON2200")
A30: Community Trust KY | B30: 2021 | C30: =SUMIFS(RawData!F:F, RawData!A:A,A30, RawData!B:B,B30, RawData!E:E,"RIAD4340") -> 74802 | D30: {=_xlfn.XLOOKUP(1,(RawData!$A:$A=A30)*(RawData!$B:$B=B30)*(RawData!$D:$D="Total Assets"),RawData!$F:$F)} -> 5201643 | E30: {=_xlfn.XLOOKUP(1,(RawData!$A:$A=A30)*(RawData!$B:$B=B30)*(RawData!$D:$D="Total Equity Capital"),RawData!$F:$F)} -> 517486 | F30: {=_xlfn.XLOOKUP(1,(RawData!$A:$A=A30)*(RawData!$B:$B=B30)*(RawData!$D:$D="Total Loans (Gross)"),RawData!$F:$F)} -> 3492715 | G30: =SUMIFS(RawData!F:F, RawData!A:A,A30, RawData!B:B,B30, RawData!E:E,"RCON2200") -> 4524118 | H30: =SUMIFS(RawData!F:F, RawData!A:A,A30, RawData!B:B,B30, RawData!E:E,"RIAD4074") -> 170944 | I30: =SUMIFS(RawData!F:F, RawData!A:A,A30, RawData!B:B,B30, RawData!E:E,"RIAD4079") -> 39517 | J30: =SUMIFS(RawData!F:F, RawData!A:A,A30, RawData!B:B,B30, RawData!E:E,"RIAD4093") -> 112084 | K30: =C30/D30 -> 0.014380456 | L30: =C30/E30 -> 0.14454884 | M30: =D30/E30 -> 10.051756 | N30: =F30/D30 -> 0.6714638 | O30: =F30/G30 -> 0.7720212 | P30: =J30/(H30+I30) -> 0.53256423 | R30: =H1 -> NII | S30: =_xlfn.FORMULATEXT(H2) -> =SUMIFS(RawData!F:F, RawData!A:A,A2, RawData!B:B,B2, RawData!E:E,"RIAD4074")
A31: Community Trust KY | B31: 2020 | C31: =SUMIFS(RawData!F:F, RawData!A:A,A31, RawData!B:B,B31, RawData!E:E,"RIAD4340") -> 60471 | D31: {=_xlfn.XLOOKUP(1,(RawData!$A:$A=A31)*(RawData!$B:$B=B31)*(RawData!$D:$D="Total Assets"),RawData!$F:$F)} -> 4986734 | E31: {=_xlfn.XLOOKUP(1,(RawData!$A:$A=A31)*(RawData!$B:$B=B31)*(RawData!$D:$D="Total Equity Capital"),RawData!$F:$F)} -> 493772 | F31: {=_xlfn.XLOOKUP(1,(RawData!$A:$A=A31)*(RawData!$B:$B=B31)*(RawData!$D:$D="Total Loans (Gross)"),RawData!$F:$F)} -> 3347980 | G31: =SUMIFS(RawData!F:F, RawData!A:A,A31, RawData!B:B,B31, RawData!E:E,"RCON2200") -> 4321569 | H31: =SUMIFS(RawData!F:F, RawData!A:A,A31, RawData!B:B,B31, RawData!E:E,"RIAD4074") -> 162308 | I31: =SUMIFS(RawData!F:F, RawData!A:A,A31, RawData!B:B,B31, RawData!E:E,"RIAD4079") -> 37904 | J31: =SUMIFS(RawData!F:F, RawData!A:A,A31, RawData!B:B,B31, RawData!E:E,"RIAD4093") -> 108556 | K31: =C31/D31 -> 0.012126374 | L31: =C31/E31 -> 0.12246745 | M31: =D31/E31 -> 10.099264 | N31: =F31/D31 -> 0.6713773 | O31: =F31/G31 -> 0.774714 | P31: =J31/(H31+I31) -> 0.54220526 | R31: =I1 -> Noninterest Income | S31: =_xlfn.FORMULATEXT(I2) -> =SUMIFS(RawData!F:F, RawData!A:A,A2, RawData!B:B,B2, RawData!E:E,"RIAD4079")
A32: Rockland Trust | B32: 2025 | C32: =SUMIFS(RawData!F:F, RawData!A:A,A32, RawData!B:B,B32, RawData!E:E,"RIAD4340") -> 197571 | D32: {=_xlfn.XLOOKUP(1,(RawData!$A:$A=A32)*(RawData!$B:$B=B32)*(RawData!$D:$D="Total Assets"),RawData!$F:$F)} -> 20640447 | E32: {=_xlfn.XLOOKUP(1,(RawData!$A:$A=A32)*(RawData!$B:$B=B32)*(RawData!$D:$D="Total Equity Capital"),RawData!$F:$F)} -> 2089063 | F32: {=_xlfn.XLOOKUP(1,(RawData!$A:$A=A32)*(RawData!$B:$B=B32)*(RawData!$D:$D="Total Loans (Gross)"),RawData!$F:$F)} -> 16701337 | G32: =SUMIFS(RawData!F:F, RawData!A:A,A32, RawData!B:B,B32, RawData!E:E,"RCON2200") -> 17864287 | H32: =SUMIFS(RawData!F:F, RawData!A:A,A32, RawData!B:B,B32, RawData!E:E,"RIAD4074") -> 575302 | I32: =SUMIFS(RawData!F:F, RawData!A:A,A32, RawData!B:B,B32, RawData!E:E,"RIAD4079") -> 120908 | J32: =SUMIFS(RawData!F:F, RawData!A:A,A32, RawData!B:B,B32, RawData!E:E,"RIAD4093") -> 405586 | K32: =C32/D32 -> 0.0095720311 | L32: =C32/E32 -> 0.094573979 | M32: =D32/E32 -> 9.8802415 | N32: =F32/D32 -> 0.80915578 | O32: =F32/G32 -> 0.93490084 | P32: =J32/(H32+I32) -> 0.58256273 | R32: =J1 -> Noninterest Expense | S32: =_xlfn.FORMULATEXT(J2) -> =SUMIFS(RawData!F:F, RawData!A:A,A2, RawData!B:B,B2, RawData!E:E,"RIAD4093")
A33: Rockland Trust | B33: 2024 | C33: =SUMIFS(RawData!F:F, RawData!A:A,A33, RawData!B:B,B33, RawData!E:E,"RIAD4340") -> 178520 | D33: {=_xlfn.XLOOKUP(1,(RawData!$A:$A=A33)*(RawData!$B:$B=B33)*(RawData!$D:$D="Total Assets"),RawData!$F:$F)} -> 19988312 | E33: {=_xlfn.XLOOKUP(1,(RawData!$A:$A=A33)*(RawData!$B:$B=B33)*(RawData!$D:$D="Total Equity Capital"),RawData!$F:$F)} -> 2001488 | F33: {=_xlfn.XLOOKUP(1,(RawData!$A:$A=A33)*(RawData!$B:$B=B33)*(RawData!$D:$D="Total Loans (Gross)"),RawData!$F:$F)} -> 16184905 | G33: =SUMIFS(RawData!F:F, RawData!A:A,A33, RawData!B:B,B33, RawData!E:E,"RCON2200") -> 17302881 | H33: =SUMIFS(RawData!F:F, RawData!A:A,A33, RawData!B:B,B33, RawData!E:E,"RIAD4074") -> 553481 | I33: =SUMIFS(RawData!F:F, RawData!A:A,A33, RawData!B:B,B33, RawData!E:E,"RIAD4079") -> 118244 | J33: =SUMIFS(RawData!F:F, RawData!A:A,A33, RawData!B:B,B33, RawData!E:E,"RIAD4093") -> 394872 | K33: =C33/D33 -> 0.0089312194 | L33: =C33/E33 -> 0.08919364 | M33: =D33/E33 -> 9.9867259 | N33: =F33/D33 -> 0.80971845 | O33: =F33/G33 -> 0.93538787 | P33: =J33/(H33+I33) -> 0.58784771 | R33: =K1 -> ROA | S33: =_xlfn.FORMULATEXT(K2) -> =C2/D2
A34: Rockland Trust | B34: 2023 | C34: =SUMIFS(RawData!F:F, RawData!A:A,A34, RawData!B:B,B34, RawData!E:E,"RIAD4340") -> 246572 | D34: {=_xlfn.XLOOKUP(1,(RawData!$A:$A=A34)*(RawData!$B:$B=B34)*(RawData!$D:$D="Total Assets"),RawData!$F:$F)} -> 19352632 | E34: {=_xlfn.XLOOKUP(1,(RawData!$A:$A=A34)*(RawData!$B:$B=B34)*(RawData!$D:$D="Total Equity Capital"),RawData!$F:$F)} -> 2920804 | F34: {=_xlfn.XLOOKUP(1,(RawData!$A:$A=A34)*(RawData!$B:$B=B34)*(RawData!$D:$D="Total Loans (Gross)"),RawData!$F:$F)} -> 14284438 | G34: =SUMIFS(RawData!F:F, RawData!A:A,A34, RawData!B:B,B34, RawData!E:E,"RCON2200") -> 14979650 | H34: =SUMIFS(RawData!F:F, RawData!A:A,A34, RawData!B:B,B34, RawData!E:E,"RIAD4074") -> 621040 | I34: =SUMIFS(RawData!F:F, RawData!A:A,A34, RawData!B:B,B34, RawData!E:E,"RIAD4079") -> 118373 | J34: =SUMIFS(RawData!F:F, RawData!A:A,A34, RawData!B:B,B34, RawData!E:E,"RIAD4093") -> 392154 | K34: =C34/D34 -> 0.012741006 | L34: =C34/E34 -> 0.084419222 | M34: =D34/E34 -> 6.6257893 | N34: =F34/D34 -> 0.73811345 | O34: =F34/G34 -> 0.95358957 | P34: =J34/(H34+I34) -> 0.53035854 | R34: =L1 -> ROE | S34: =_xlfn.FORMULATEXT(L2) -> =C2/E2
A35: Rockland Trust | B35: 2022 | C35: =SUMIFS(RawData!F:F, RawData!A:A,A35, RawData!B:B,B35, RawData!E:E,"RIAD4340") -> 268324 | D35: {=_xlfn.XLOOKUP(1,(RawData!$A:$A=A35)*(RawData!$B:$B=B35)*(RawData!$D:$D="Total Assets"),RawData!$F:$F)} -> 18535579 | E35: {=_xlfn.XLOOKUP(1,(RawData!$A:$A=A35)*(RawData!$B:$B=B35)*(RawData!$D:$D="Total Equity Capital"),RawData!$F:$F)} -> 2848513 | F35: {=_xlfn.XLOOKUP(1,(RawData!$A:$A=A35)*(RawData!$B:$B=B35)*(RawData!$D:$D="Total Loans (Gross)"),RawData!$F:$F)} -> 13747919 | G35: =SUMIFS(RawData!F:F, RawData!A:A,A35, RawData!B:B,B35, RawData!E:E,"RCON2200") -> 15356636 | H35: =SUMIFS(RawData!F:F, RawData!A:A,A35, RawData!B:B,B35, RawData!E:E,"RIAD4074") -> 553959 | I35: =SUMIFS(RawData!F:F, RawData!A:A,A35, RawData!B:B,B35, RawData!E:E,"RIAD4079") -> 102074 | J35: =SUMIFS(RawData!F:F, RawData!A:A,A35, RawData!B:B,B35, RawData!E:E,"RIAD4093") -> 404241 | K35: =C35/D35 -> 0.01447616 | L35: =C35/E35 -> 0.09419792 | M35: =D35/E35 -> 6.507107 | N35: =F35/D35 -> 0.74170432 | O35: =F35/G35 -> 0.89524288 | P35: =J35/(H35+I35) -> 0.61619004 | R35: =M1 -> Equity Multiplier | S35: =_xlfn.FORMULATEXT(M2) -> =D2/E2
A36: Rockland Trust | B36: 2021 | C36: =SUMIFS(RawData!F:F, RawData!A:A,A36, RawData!B:B,B36, RawData!E:E,"RIAD4340") -> 189884 | D36: {=_xlfn.XLOOKUP(1,(RawData!$A:$A=A36)*(RawData!$B:$B=B36)*(RawData!$D:$D="Total Assets"),RawData!$F:$F)} -> 18039393 | E36: {=_xlfn.XLOOKUP(1,(RawData!$A:$A=A36)*(RawData!$B:$B=B36)*(RawData!$D:$D="Total Equity Capital"),RawData!$F:$F)} -> 2685880 | F36: {=_xlfn.XLOOKUP(1,(RawData!$A:$A=A36)*(RawData!$B:$B=B36)*(RawData!$D:$D="Total Loans (Gross)"),RawData!$F:$F)} -> 12602765 | G36: =SUMIFS(RawData!F:F, RawData!A:A,A36, RawData!B:B,B36, RawData!E:E,"RCON2200") -> 15212141 | H36: =SUMIFS(RawData!F:F, RawData!A:A,A36, RawData!B:B,B36, RawData!E:E,"RIAD4074") -> 500528 | I36: =SUMIFS(RawData!F:F, RawData!A:A,A36, RawData!B:B,B36, RawData!E:E,"RIAD4079") -> 115946 | J36: =SUMIFS(RawData!F:F, RawData!A:A,A36, RawData!B:B,B36, RawData!E:E,"RIAD4093") -> 395734 | K36: =C36/D36 -> 0.010526075 | L36: =C36/E36 -> 0.070697127 | M36: =D36/E36 -> 6.7163809 | N36: =F36/D36 -> 0.69862467 | O36: =F36/G36 -> 0.82846754 | P36: =J36/(H36+I36) -> 0.64193137 | R36: =N1 -> Loan/Asset | S36: =_xlfn.FORMULATEXT(N2) -> =F2/D2
A37: Rockland Trust | B37: 2020 | C37: =SUMIFS(RawData!F:F, RawData!A:A,A37, RawData!B:B,B37, RawData!E:E,"RIAD4340") -> 129857 | D37: {=_xlfn.XLOOKUP(1,(RawData!$A:$A=A37)*(RawData!$B:$B=B37)*(RawData!$D:$D="Total Assets"),RawData!$F:$F)} -> 17003476 | E37: {=_xlfn.XLOOKUP(1,(RawData!$A:$A=A37)*(RawData!$B:$B=B37)*(RawData!$D:$D="Total Equity Capital"),RawData!$F:$F)} -> 2470655 | F37: {=_xlfn.XLOOKUP(1,(RawData!$A:$A=A37)*(RawData!$B:$B=B37)*(RawData!$D:$D="Total Loans (Gross)"),RawData!$F:$F)} -> 12368770 | G37: =SUMIFS(RawData!F:F, RawData!A:A,A37, RawData!B:B,B37, RawData!E:E,"RCON2200") -> 14231087 | H37: =SUMIFS(RawData!F:F, RawData!A:A,A37, RawData!B:B,B37, RawData!E:E,"RIAD4074") -> 477880 | I37: =SUMIFS(RawData!F:F, RawData!A:A,A37, RawData!B:B,B37, RawData!E:E,"RIAD4079") -> 112642 | J37: =SUMIFS(RawData!F:F, RawData!A:A,A37, RawData!B:B,B37, RawData!E:E,"RIAD4093") -> 378436 | K37: =C37/D37 -> 0.0076370855 | L37: =C37/E37 -> 0.052559746 | M37: =D37/E37 -> 6.8821734 | N37: =F37/D37 -> 0.72742597 | O37: =F37/G37 -> 0.8691374 | P37: =J37/(H37+I37) -> 0.64084996 | R37: =O1 -> Loan/Deposit | S37: =_xlfn.FORMULATEXT(O2) -> =F2/G2
R38: =P1 -> Efficiency Ratio | S38: =_xlfn.FORMULATEXT(P2) -> =J2/(H2+I2)

Sheet FIN432_US_Commercial_Bank_Finan
A1: Table 1: 6-Year Profitability & Stability
A2: Bank | B2: Avg ROA | C2: ROA Std Dev | D2: Avg ROE | E2: ROE Std Dev
A3: JPM | B3: =AVERAGEIFS('Calculated Ratio'!$K:$K,'Calculated Ratio'!$A:$A,$A3) -> 0.011841695 | C3: {=_xlfn.STDEV.S(_xlfn._xlws.FILTER('Calculated Ratio'!$K:$K,'Calculated Ratio'!$A:$A=$A3))} -> 0.0031988938 | D3: =AVERAGEIFS('Calculated Ratio'!$L:$L,'Calculated Ratio'!$A:$A,$A3) -> 0.14103247 | E3: {=_xlfn.STDEV.S(_xlfn._xlws.FILTER('Calculated Ratio'!$L:$L,'Calculated Ratio'!$A:$A=$A3))} -> 0.035075286
A4: BAC | B4: =AVERAGEIFS('Calculated Ratio'!$K:$K,'Calculated Ratio'!$A:$A,$A4) -> 0.056230486 | C4: {=_xlfn.STDEV.S(_xlfn._xlws.FILTER('Calculated Ratio'!$K:$K,'Calculated Ratio'!$A:$A=$A4))} -> 0.01086653 | D4: =AVERAGEIFS('Calculated Ratio'!$L:$L,'Calculated Ratio'!$A:$A,$A4) -> 0.67347165 | E4: {=_xlfn.STDEV.S(_xlfn._xlws.FILTER('Calculated Ratio'!$L:$L,'Calculated Ratio'!$A:$A=$A4))} -> 0.12048889
A5: PNC | B5: =AVERAGEIFS('Calculated Ratio'!$K:$K,'Calculated Ratio'!$A:$A,$A5) -> 0.010967965 | C5: {=_xlfn.STDEV.S(_xlfn._xlws.FILTER('Calculated Ratio'!$K:$K,'Calculated Ratio'!$A:$A=$A5))} -> 0.0011907648 | D5: =AVERAGEIFS('Calculated Ratio'!$L:$L,'Calculated Ratio'!$A:$A,$A5) -> 0.11213436 | E5: {=_xlfn.STDEV.S(_xlfn._xlws.FILTER('Calculated Ratio'!$L:$L,'Calculated Ratio'!$A:$A=$A5))} -> 0.011381737
A6: TRUIST | B6: =AVERAGEIFS('Calculated Ratio'!$K:$K,'Calculated Ratio'!$A:$A,$A6) -> 0.0086213383 | C6: {=_xlfn.STDEV.S(_xlfn._xlws.FILTER('Calculated Ratio'!$K:$K,'Calculated Ratio'!$A:$A=$A6))} -> 0.0030092656 | D6: =AVERAGEIFS('Calculated Ratio'!$L:$L,'Calculated Ratio'!$A:$A,$A6) -> 0.091699739 | E6: {=_xlfn.STDEV.S(_xlfn._xlws.FILTER('Calculated Ratio'!$L:$L,'Calculated Ratio'!$A:$A=$A6))} -> 0.032705824
A7: Community Trust KY | B7: =AVERAGEIFS('Calculated Ratio'!$K:$K,'Calculated Ratio'!$A:$A,$A7) -> 0.014750506 | C7: {=_xlfn.STDEV.S(_xlfn._xlws.FILTER('Calculated Ratio'!$K:$K,'Calculated Ratio'!$A:$A=$A7))} -> 0.0013723665 | D7: =AVERAGEIFS('Calculated Ratio'!$L:$L,'Calculated Ratio'!$A:$A,$A7) -> 0.14747556 | E7: {=_xlfn.STDEV.S(_xlfn._xlws.FILTER('Calculated Ratio'!$L:$L,'Calculated Ratio'!$A:$A=$A7))} -> 0.012888366
A8: Rockland Trust | B8: =AVERAGEIFS('Calculated Ratio'!$K:$K,'Calculated Ratio'!$A:$A,$A8) -> 0.010647263 | C8: {=_xlfn.STDEV.S(_xlfn._xlws.FILTER('Calculated Ratio'!$K:$K,'Calculated Ratio'!$A:$A=$A8))} -> 0.0025385426 | D8: =AVERAGEIFS('Calculated Ratio'!$L:$L,'Calculated Ratio'!$A:$A,$A8) -> 0.080940272 | E8: {=_xlfn.STDEV.S(_xlfn._xlws.FILTER('Calculated Ratio'!$L:$L,'Calculated Ratio'!$A:$A=$A8))} -> 0.016445307
A10: Table 2: Risk & Leverage Snapshot (2025)
A11: Bank | B11: Loan/Asset (2025) | C11: Loan/Deposit (2025) | D11: Equity Multiplier (2025)
A12: JPM | B12: {=_xlfn.XLOOKUP($A12&2025,'Calculated Ratio'!$A:$A&'Calculated Ratio'!$B:$B,'Calculated Ratio'!$N:$N)} -> 0.37691631 | C12: {=_xlfn.XLOOKUP($A12&2025,'Calculated Ratio'!$A:$A&'Calculated Ratio'!$B:$B,'Calculated Ratio'!$O:$O)} -> 0.61368416 | D12: {=_xlfn.XLOOKUP($A12&2025,'Calculated Ratio'!$A:$A&'Calculated Ratio'!$B:$B,'Calculated Ratio'!$M:$M)} -> 11.524873
A13: BAC | B13: {=_xlfn.XLOOKUP($A13&2025,'Calculated Ratio'!$A:$A&'Calculated Ratio'!$B:$B,'Calculated Ratio'!$N:$N)} -> 0.62276975 | C13: {=_xlfn.XLOOKUP($A13&2025,'Calculated Ratio'!$A:$A&'Calculated Ratio'!$B:$B,'Calculated Ratio'!$O:$O)} -> 0.69150943 | D13: {=_xlfn.XLOOKUP($A13&2025,'Calculated Ratio'!$A:$A&'Calculated Ratio'!$B:$B,'Calculated Ratio'!$M:$M)} -> 11.653465
A14: PNC | B14: {=_xlfn.XLOOKUP($A14&2025,'Calculated Ratio'!$A:$A&'Calculated Ratio'!$B:$B,'Calculated Ratio'!$N:$N)} -> 0.57836025 | C14: {=_xlfn.XLOOKUP($A14&2025,'Calculated Ratio'!$A:$A&'Calculated Ratio'!$B:$B,'Calculated Ratio'!$O:$O)} -> 0.73693634 | D14: {=_xlfn.XLOOKUP($A14&2025,'Calculated Ratio'!$A:$A&'Calculated Ratio'!$B:$B,'Calculated Ratio'!$M:$M)} -> 9.8016152
A15: TRUIST | B15: {=_xlfn.XLOOKUP($A15&2025,'Calculated Ratio'!$A:$A&'Calculated Ratio'!$B:$B,'Calculated Ratio'!$N:$N)} -> 0.59387831 | C15: {=_xlfn.XLOOKUP($A15&2025,'Calculated Ratio'!$A:$A&'Calculated Ratio'!$B:$B,'Calculated Ratio'!$O:$O)} -> 0.77176813 | D15: {=_xlfn.XLOOKUP($A15&2025,'Calculated Ratio'!$A:$A&'Calculated Ratio'!$B:$B,'Calculated Ratio'!$M:$M)} -> 10.802419
A16: Community Trust KY | B16: {=_xlfn.XLOOKUP($A16&2025,'Calculated Ratio'!$A:$A&'Calculated Ratio'!$B:$B,'Calculated Ratio'!$N:$N)} -> 0.69386474 | C16: {=_xlfn.XLOOKUP($A16&2025,'Calculated Ratio'!$A:$A&'Calculated Ratio'!$B:$B,'Calculated Ratio'!$O:$O)} -> 0.79286899 | D16: {=_xlfn.XLOOKUP($A16&2025,'Calculated Ratio'!$A:$A&'Calculated Ratio'!$B:$B,'Calculated Ratio'!$M:$M)} -> 9.7413206
A17: Rockland Trust | B17: {=_xlfn.XLOOKUP($A17&2025,'Calculated Ratio'!$A:$A&'Calculated Ratio'!$B:$B,'Calculated Ratio'!$N:$N)} -> 0.80915578 | C17: {=_xlfn.XLOOKUP($A17&2025,'Calculated Ratio'!$A:$A&'Calculated Ratio'!$B:$B,'Calculated Ratio'!$O:$O)} -> 0.93490084 | D17: {=_xlfn.XLOOKUP($A17&2025,'Calculated Ratio'!$A:$A&'Calculated Ratio'!$B:$B,'Calculated Ratio'!$M:$M)} -> 9.8802415
A19: TABLE 3 — Revenue Structure (2025)
A20: Bank | B20: NII (2025) | C20: Noninterest Income (2025) | D20: Efficiency Ratio (2025)
A21: JPM | B21: {=_xlfn.XLOOKUP($A21&2025,'Calculated Ratio'!$A:$A&'Calculated Ratio'!$B:$B,'Calculated Ratio'!$H:$H)} -> 97846000 | C21: {=_xlfn.XLOOKUP($A21&2025,'Calculated Ratio'!$A:$A&'Calculated Ratio'!$B:$B,'Calculated Ratio'!$I:$I)} -> 66240000 | D21: {=_xlfn.XLOOKUP($A21&2025,'Calculated Ratio'!$A:$A&'Calculated Ratio'!$B:$B,'Calculated Ratio'!$P:$P)} -> 0.52489548
A22: BAC | B22: {=_xlfn.XLOOKUP($A22&2025,'Calculated Ratio'!$A:$A&'Calculated Ratio'!$B:$B,'Calculated Ratio'!$H:$H)} -> 238000 | C22: {=_xlfn.XLOOKUP($A22&2025,'Calculated Ratio'!$A:$A&'Calculated Ratio'!$B:$B,'Calculated Ratio'!$I:$I)} -> 1000 | D22: {=_xlfn.XLOOKUP($A22&2025,'Calculated Ratio'!$A:$A&'Calculated Ratio'!$B:$B,'Calculated Ratio'!$P:$P)} -> 0.52301255
A23: PNC | B23: {=_xlfn.XLOOKUP($A23&2025,'Calculated Ratio'!$A:$A&'Calculated Ratio'!$B:$B,'Calculated Ratio'!$H:$H)} -> 15135750 | C23: {=_xlfn.XLOOKUP($A23&2025,'Calculated Ratio'!$A:$A&'Calculated Ratio'!$B:$B,'Calculated Ratio'!$I:$I)} -> 7780792 | D23: {=_xlfn.XLOOKUP($A23&2025,'Calculated Ratio'!$A:$A&'Calculated Ratio'!$B:$B,'Calculated Ratio'!$P:$P)} -> 0.57817964
A24: TRUIST | B24: {=_xlfn.XLOOKUP($A24&2025,'Calculated Ratio'!$A:$A&'Calculated Ratio'!$B:$B,'Calculated Ratio'!$H:$H)} -> 14812000 | C24: {=_xlfn.XLOOKUP($A24&2025,'Calculated Ratio'!$A:$A&'Calculated Ratio'!$B:$B,'Calculated Ratio'!$I:$I)} -> 4527000 | D24: {=_xlfn.XLOOKUP($A24&2025,'Calculated Ratio'!$A:$A&'Calculated Ratio'!$B:$B,'Calculated Ratio'!$P:$P)} -> 0.55897409
A25: Community Trust KY | B25: {=_xlfn.XLOOKUP($A25&2025,'Calculated Ratio'!$A:$A&'Calculated Ratio'!$B:$B,'Calculated Ratio'!$H:$H)} -> 221396 | C25: {=_xlfn.XLOOKUP($A25&2025,'Calculated Ratio'!$A:$A&'Calculated Ratio'!$B:$B,'Calculated Ratio'!$I:$I)} -> 44791 | D25: {=_xlfn.XLOOKUP($A25&2025,'Calculated Ratio'!$A:$A&'Calculated Ratio'!$B:$B,'Calculated Ratio'!$P:$P)} -> 0.48446017
A26: Rockland Trust | B26: {=_xlfn.XLOOKUP($A26&2025,'Calculated Ratio'!$A:$A&'Calculated Ratio'!$B:$B,'Calculated Ratio'!$H:$H)} -> 575302 | C26: {=_xlfn.XLOOKUP($A26&2025,'Calculated Ratio'!$A:$A&'Calculated Ratio'!$B:$B,'Calculated Ratio'!$I:$I)} -> 120908 | D26: {=_xlfn.XLOOKUP($A26&2025,'Calculated Ratio'!$A:$A&'Calculated Ratio'!$B:$B,'Calculated Ratio'!$P:$P)} -> 0.58256273

Sheet Visual Analysis Sheet
